MANIFEST.in
README.rst
setup.py
docs/HISTORY.txt
docs/LICENSE.GPL
docs/LICENSE.txt
docs/example-internet-workflow-specification.txt
docs/screenshot-sharing-overlay.png
docs/screenshot-workflow-details.png
ftw/__init__.py
ftw.lawgiver.egg-info/PKG-INFO
ftw.lawgiver.egg-info/SOURCES.txt
ftw.lawgiver.egg-info/dependency_links.txt
ftw.lawgiver.egg-info/entry_points.txt
ftw.lawgiver.egg-info/namespace_packages.txt
ftw.lawgiver.egg-info/not-zip-safe
ftw.lawgiver.egg-info/requires.txt
ftw.lawgiver.egg-info/top_level.txt
ftw/lawgiver/__init__.py
ftw/lawgiver/actiongroups.py
ftw/lawgiver/collector.py
ftw/lawgiver/commands.py
ftw/lawgiver/configure.zcml
ftw/lawgiver/discovery.py
ftw/lawgiver/exceptions.py
ftw/lawgiver/generator.py
ftw/lawgiver/i18nbuilder.py
ftw/lawgiver/interfaces.py
ftw/lawgiver/lawgiver.zcml
ftw/lawgiver/localroles.py
ftw/lawgiver/localroles.zcml
ftw/lawgiver/meta.py
ftw/lawgiver/meta.zcml
ftw/lawgiver/overrides.zcml
ftw/lawgiver/profiles.zcml
ftw/lawgiver/schema.py
ftw/lawgiver/setuphandlers.py
ftw/lawgiver/testing.py
ftw/lawgiver/updater.py
ftw/lawgiver/utils.py
ftw/lawgiver/variables.py
ftw/lawgiver/Extensions/install.py
ftw/lawgiver/browser/__init__.py
ftw/lawgiver/browser/configure.zcml
ftw/lawgiver/browser/details.py
ftw/lawgiver/browser/modifystatus.py
ftw/lawgiver/browser/sharing.py
ftw/lawgiver/browser/speclisting.py
ftw/lawgiver/browser/resources/lawgiver-icon.png
ftw/lawgiver/browser/resources/sharing.js
ftw/lawgiver/browser/templates/details.pt
ftw/lawgiver/browser/templates/import-confirmation.pt
ftw/lawgiver/browser/templates/sharing-describe-role.pt
ftw/lawgiver/browser/templates/speclisting.pt
ftw/lawgiver/locales/ftw.lawgiver-manual.pot
ftw/lawgiver/locales/ftw.lawgiver.pot
ftw/lawgiver/locales/de/LC_MESSAGES/ftw.lawgiver.po
ftw/lawgiver/profiles/default/browserlayer.xml
ftw/lawgiver/profiles/default/controlpanel.xml
ftw/lawgiver/profiles/default/jsregistry.xml
ftw/lawgiver/profiles/default/metadata.xml
ftw/lawgiver/profiles/uninstall/browserlayer.xml
ftw/lawgiver/profiles/uninstall/ftw.lawgiver.various.txt
ftw/lawgiver/profiles/uninstall/jsregistry.xml
ftw/lawgiver/tests/__init__.py
ftw/lawgiver/tests/base.py
ftw/lawgiver/tests/builders.py
ftw/lawgiver/tests/generator.zcml
ftw/lawgiver/tests/helpers.py
