Metadata-Version: 2.1
Name: ftw.lawgiver
Version: 1.17.4
Summary: Generate your Plone workflows by describing it in plain text with a DSL.
Home-page: https://github.com/4teamwork/ftw.lawgiver
Author: 4teamwork AG
Author-email: mailto:info@4teamwork.ch
License: GPL2
Keywords: ftw lawgiver generate workflows dsl
Platform: UNKNOWN
Classifier: Framework :: Plone
Classifier: Framework :: Plone :: 4.3
Classifier: Framework :: Plone :: 5.1
Classifier: Intended Audience :: Developers
Classifier: Topic :: Software Development :: Libraries :: Python Modules
Provides-Extra: deletepermission
Provides-Extra: tests
